Metadata-Version: 1.1
Name: marcxml-parser
Version: 1.2.2
Summary: MARC XML / OAI parser, with few highlevel getters.
Home-page: https://github.com/edeposit/marcxml_parser
Author: Edeposit team
Author-email: edeposit@email.cz
License: MIT
Platform: UNKNOWN
Classifier: Programming Language :: Python :: 2.7
Classifier: License :: OSI Approved :: MIT License
Classifier: Topic :: Software Development :: Libraries :: Python Modules
